aurastamp/__init__.py
aurastamp/aurastamp_image.py
aurastamp/main.py
aurastamp-1.0.3.dist-info/METADATA
aurastamp-1.0.3.dist-info/WHEEL
aurastamp-1.0.3.dist-info/top_level.txt
aurastamp-1.0.3.dist-info/RECORD
