Metadata-Version: 2.1
Name: aurastamp
Version: 1.0.3
Summary: aurastamp api for python
Home-page: UNKNOWN
Author: stegato
Author-email: admin@stegato.com
License: UNKNOWN
Keywords: aurastamp,steganography
Platform: UNKNOWN
Requires-Python: >=3.6
Requires-Dist: requests
Requires-Dist: requests-toolbelt
Requires-Dist: Pillow
